npy_patcher.cpython-310-x86_64-linux-gnu.so
npy_patcher-1.3.0.dist-info/LICENSE
npy_patcher-1.3.0.dist-info/RECORD
npy_patcher-1.3.0.dist-info/top_level.txt
npy_patcher-1.3.0.dist-info/METADATA
npy_patcher-1.3.0.dist-info/WHEEL
npy_patcher.libs/libstdc++-a9383cce.so.6.0.28
npy_patcher.libs/libgcc_s-a04fdf82.so.1
npy_patcher/__init__.pyi
npy_patcher/py.typed
