Metadata-Version: 2.1
Name: npy-patcher
Version: 1.3.0
Summary: C++ based NumPy N-Dimesional patch extraction.
Home-page: https://github.com/m-lyon/npy-cpp-patches
Download-URL: https://https://github.com/m-lyon/npy-cpp-patches/archive/v1.3.0.tar.gz
Author: Matthew Lyon
Author-email: matthewlyon18@gmail.com
License: MIT License
Classifier: Programming Language :: Python
Classifier: Operating System :: Unix
Classifier: Operating System :: MacOS
Requires-Python: >=3.6
License-File: LICENSE
